mm_kermac/__init__.py
mm_kermac/common.py
mm_kermac/helpers.py
mm_kermac/stack_ptx_types.py
mm_kermac/hyper_semiring/__init__.py
mm_kermac/hyper_semiring/hyper_semiring.py
mm_kermac/hyper_semiring/zoo/gemm.py
mm_kermac/hyper_semiring/zoo/norm_L1.py
mm_kermac/hyper_semiring/zoo/norm_L2.py
mm_kermac/hyper_semiring/zoo/norm_Lp.py
mm_kermac/hyper_semiring_gradient/__init__.py
mm_kermac/hyper_semiring_gradient/hyper_semiring_gradient.py
mm_kermac/hyper_semiring_gradient/zoo/norm_L1.py
mm_kermac/hyper_semiring_gradient/zoo/norm_L2.py
mm_kermac/hyper_semiring_gradient/zoo/norm_Lp.py
mm_kermac/ptx_inject_cache/function_db_key.py
mm_kermac/ptx_inject_cache/function_db_value.py
mm_kermac/ptx_inject_cache/paths.py
mm_kermac/ptx_inject_cache/ptx_inject_cache.py
mm_kermac/ptx_inject_cache/ptx_inject_types.py
include/kermac_internal_common.cuh
kernels/base_semiring.cuh
kernels/base_semiring_grad.cuh
kernels/template_hyper_semiring.cuh
kernels/template_hyper_semiring_gradient.cuh
thirdparty/cutlass/include/cute/config.hpp
thirdparty/cutlass/include/cute/int_tuple.hpp
thirdparty/cutlass/include/cute/layout.hpp
thirdparty/cutlass/include/cute/layout_composed.hpp
thirdparty/cutlass/include/cute/pointer.hpp
thirdparty/cutlass/include/cute/pointer_base.hpp
thirdparty/cutlass/include/cute/pointer_flagged.hpp
thirdparty/cutlass/include/cute/pointer_sparse.hpp
thirdparty/cutlass/include/cute/pointer_swizzle.hpp
thirdparty/cutlass/include/cute/stride.hpp
thirdparty/cutlass/include/cute/swizzle.hpp
thirdparty/cutlass/include/cute/swizzle_layout.hpp
thirdparty/cutlass/include/cute/tensor.hpp
thirdparty/cutlass/include/cute/tensor_impl.hpp
thirdparty/cutlass/include/cute/tensor_zip.hpp
thirdparty/cutlass/include/cute/underscore.hpp
thirdparty/cutlass/include/cute/algorithm/axpby.hpp
thirdparty/cutlass/include/cute/algorithm/clear.hpp
thirdparty/cutlass/include/cute/algorithm/cooperative_copy.hpp
thirdparty/cutlass/include/cute/algorithm/cooperative_gemm.hpp
mm_kermac-1.0.0.dist-info/METADATA
mm_kermac-1.0.0.dist-info/WHEEL
mm_kermac-1.0.0.dist-info/licenses/LICENSE
mm_kermac-1.0.0.dist-info/RECORD
