Metadata-Version: 2.4
Name: mm-kermac
Version: 1.0.0
Summary: Dynamically compiled hyper semirings for Pytorch using PTX Inject and Stack PTX
Project-URL: Homepage, https://github.com/MetaMachines/mm-kermac-py
Project-URL: Repository, https://github.com/MetaMachines/mm-kermac-py.git
Author-email: MetaMachines LLC <contact@metamachines.co>
License: MIT
License-File: LICENSE
Classifier: Development Status :: 5 - Production/Stable
Classifier: Intended Audience :: Developers
Classifier: Intended Audience :: Science/Research
Classifier: License :: OSI Approved :: MIT License
Classifier: Operating System :: OS Independent
Classifier: Programming Language :: C
Classifier: Programming Language :: Python :: 3
Classifier: Programming Language :: Python :: 3 :: Only
Classifier: Programming Language :: Python :: 3.8
Classifier: Programming Language :: Python :: 3.9
Classifier: Programming Language :: Python :: 3.10
Classifier: Programming Language :: Python :: 3.11
Classifier: Programming Language :: Python :: 3.12
Classifier: Topic :: Scientific/Engineering
Classifier: Topic :: Scientific/Engineering :: Artificial Intelligence
Classifier: Topic :: Scientific/Engineering :: Mathematics
Classifier: Topic :: Software Development :: Compilers
Classifier: Topic :: Software Development :: Libraries
Classifier: Topic :: Software Development :: Libraries :: Python Modules
Classifier: Topic :: System :: Hardware
Requires-Python: >=3.8
Requires-Dist: cuda-toolkit[cccl]
Requires-Dist: mm-ptx>=1.0.0
Requires-Dist: numpy>=1.21
Requires-Dist: platformdirs>=3.0
Requires-Dist: torch>=2.0
Provides-Extra: cu12
Requires-Dist: cuda-core[cu12]>=0.5.0; extra == 'cu12'
Provides-Extra: cu13
Requires-Dist: cuda-core[cu13]>=0.5.0; extra == 'cu13'
